a9x_webstatistics/__init__.py
a9x_webstatistics/main.py
a9x_webstatistics/module1.py
a9x_webstatistics/updatestatistics.py
a9x_webstatistics_package-0.1.3.dist-info/LICENSE
a9x_webstatistics_package-0.1.3.dist-info/METADATA
a9x_webstatistics_package-0.1.3.dist-info/WHEEL
a9x_webstatistics_package-0.1.3.dist-info/top_level.txt
a9x_webstatistics_package-0.1.3.dist-info/RECORD
