Metadata-Version: 2.1
Name: a9x_webstatistics_package
Version: 0.1.3
Summary: Web Statistics and Analytics Package
Home-page: https://github.com/ava007/a9x-webstatistics
Author: André von Arx
Author-email: andrevonarx@bluewin.ch
Project-URL: Documentation, https://github.com/ava007/a9x-webstatistics
Project-URL: Bug Reports, https://github.com/ava007/a9x-webstatistics/issues
Project-URL: Source Code, https://github.com/ava007/a9x-webstatistics
Keywords: webstats,statistics,analytics
Classifier: Development Status :: 5 - Production/Stable
Classifier: Intended Audience :: Developers
Classifier: Topic :: Software Development :: Build Tools
Classifier: Programming Language :: Python :: 3
Classifier: Programming Language :: Python :: 3.9
Classifier: Programming Language :: Python :: 3 :: Only
Classifier: License :: OSI Approved :: MIT License
Classifier: Operating System :: OS Independent
Requires-Python: >=3.9
License-File: LICENSE
Provides-Extra: dev
Requires-Dist: check-manifest ; extra == 'dev'
